whoopy/__init__.py
whoopy/client_v1.py
whoopy/client_v2.py
whoopy/client_vu7.py
whoopy/constants.py
whoopy/example.py
whoopy/exceptions.py
whoopy/sync_wrapper.py
whoopy/handlers/__init__.py
whoopy/handlers/base_v2.py
whoopy/handlers/handler_v1.py
whoopy/handlers/handlers_v2.py
whoopy/models/__init__.py
whoopy/models/models_v1.py
whoopy/models/models_v2.py
whoopy/utils/__init__.py
whoopy/utils/auth.py
whoopy/utils/pagination.py
whoopy/utils/retry.py
whoopy/utils/throttle.py
whoopy-0.3.0.dist-info/METADATA
whoopy-0.3.0.dist-info/WHEEL
whoopy-0.3.0.dist-info/licenses/LICENSE
whoopy-0.3.0.dist-info/RECORD
