Metadata-Version: 2.4
Name: whoopy
Version: 0.3.0
Summary: Unofficial Client for the Whoop API
Project-URL: Homepage, https://github.com/felixnext/whoopy
Project-URL: Documentation, https://github.com/felixnext/whoopy#readme
Project-URL: Repository, https://github.com/felixnext/whoopy.git
Project-URL: Issues, https://github.com/felixnext/whoopy/issues
Project-URL: Changelog, https://github.com/felixnext/whoopy/releases
Author: Felix Geilert
Maintainer: Felix Geilert
License: MIT
License-File: LICENSE
Keywords: api,fitness,health,wearable,whoop
Classifier: Development Status :: 4 - Beta
Classifier: Intended Audience :: Developers
Classifier: License :: OSI Approved :: MIT License
Classifier: Programming Language :: Python :: 3
Classifier: Programming Language :: Python :: 3.10
Classifier: Programming Language :: Python :: 3.11
Classifier: Programming Language :: Python :: 3.12
Classifier: Programming Language :: Python :: 3.13
Classifier: Topic :: Internet :: WWW/HTTP
Classifier: Topic :: Software Development :: Libraries :: Python Modules
Requires-Python: >=3.10
Requires-Dist: aiohttp>=3.9.0
Requires-Dist: numpy>=1.23.0
Requires-Dist: pandas>=1.4.0
Requires-Dist: pydantic>=2.0.0
Requires-Dist: python-dateutil>=2.8.2
Requires-Dist: requests>=2.28.1
Requires-Dist: time-helper>=0.1.4
Provides-Extra: dev
Requires-Dist: black>=23.0.0; extra == 'dev'
Requires-Dist: ipython>=8.0.0; extra == 'dev'
Requires-Dist: mypy>=1.0.0; extra == 'dev'
Requires-Dist: pre-commit>=3.0.0; extra == 'dev'
Requires-Dist: pytest-asyncio>=0.21.0; extra == 'dev'
Requires-Dist: pytest-cov>=4.0.0; extra == 'dev'
Requires-Dist: pytest>=7.0.0; extra == 'dev'
Requires-Dist: ruff>=0.1.0; extra == 'dev'
Provides-Extra: explorer
Requires-Dist: plotly>=5.18.0; extra == 'explorer'
Requires-Dist: seaborn>=0.12.0; extra == 'explorer'
Requires-Dist: streamlit>=1.28.0; extra == 'explorer'
Provides-Extra: test
Requires-Dist: aioresponses>=0.7.0; extra == 'test'
Requires-Dist: pytest-asyncio>=0.21.0; extra == 'test'
Requires-Dist: pytest-cov>=4.0.0; extra == 'test'
Requires-Dist: pytest>=7.0.0; extra == 'test'
Requires-Dist: responses>=0.23.0; extra == 'test'
